[
  {
    "id": 1,
    "airlineName": "Korean Air",
    "country": "japan",
    "countryImage": "http://localhost:3333/images/country/japan.jpeg",
    "departureAirport": "ICN",
    "arrivalAirport": "NRT",
    "arrivalCountry": "일본",
    "outboundDate": "2024-07-15",
    "inboundDate": "2024-07-20",
    "price": 280000,
    "currency": "KRW",
    "promotionTag": "특가"
  },
  {
    "id": 2,
    "airlineName": "Asiana Airlines",
    "country": "hong-kong",
    "countryImage": "http://localhost:3333/images/country/hong-kong.jpeg",
    "departureAirport": "ICN",
    "arrivalAirport": "HKG",
    "arrivalCountry": "홍콩",
    "outboundDate": "2024-08-01",
    "inboundDate": "2024-08-05",
    "price": 310000,
    "currency": "KRW",
    "promotionTag": "특가"
  },
  {
    "id": 3,
    "airlineName": "Jeju Air",
    "country": "thailand",
    "countryImage": "http://localhost:3333/images/country/thailand.jpeg",
    "departureAirport": "CJU",
    "arrivalAirport": "BKK",
    "arrivalCountry": "태국",
    "outboundDate": "2024-07-10",
    "inboundDate": "2024-07-15",
    "price": 250000,
    "currency": "KRW",
    "promotionTag": "한정"
  },
  {
    "id": 4,
    "airlineName": "T'way Air",
    "country": "singapore",
    "countryImage": "http://localhost:3333/images/country/singapore.jpeg",
    "departureAirport": "ICN",
    "arrivalAirport": "SIN",
    "arrivalCountry": "싱가포르",
    "outboundDate": "2024-09-10",
    "inboundDate": "2024-09-20",
    "price": 400000,
    "currency": "KRW",
    "promotionTag": "특가"
  },
  {
    "id": 5,
    "airlineName": "Vietnam Airlines",
    "country": "vietnam",
    "countryImage": "http://localhost:3333/images/country/vietnam.jpeg",
    "departureAirport": "ICN",
    "arrivalAirport": "HAN",
    "arrivalCountry": "베트남",
    "outboundDate": "2024-07-05",
    "inboundDate": "2024-07-10",
    "price": 220000,
    "currency": "KRW",
    "promotionTag": "특가"
  },
  {
    "id": 6,
    "airlineName": "Cathay Pacific",
    "country": "hong-kong",
    "countryImage": "http://localhost:3333/images/country/hong-kong.jpeg",
    "departureAirport": "ICN",
    "arrivalAirport": "HKG",
    "arrivalCountry": "홍콩",
    "outboundDate": "2024-08-15",
    "inboundDate": "2024-08-20",
    "price": 330000,
    "currency": "KRW",
    "promotionTag": "한정"
  },
  {
    "id": 7,
    "airlineName": "AirAsia",
    "country": "malaysia",
    "countryImage": "http://localhost:3333/images/country/malaysia.jpeg",
    "departureAirport": "ICN",
    "arrivalAirport": "KUL",
    "arrivalCountry": "말레이시아",
    "outboundDate": "2024-07-22",
    "inboundDate": "2024-07-27",
    "price": 280000,
    "currency": "KRW",
    "promotionTag": "특가"
  },
  {
    "id": 8,
    "airlineName": "Singapore Airlines",
    "country": "singapore",
    "countryImage": "http://localhost:3333/images/country/singapore.jpeg",
    "departureAirport": "ICN",
    "arrivalAirport": "SIN",
    "arrivalCountry": "싱가포르",
    "outboundDate": "2024-08-30",
    "inboundDate": "2024-09-04",
    "price": 420000,
    "currency": "KRW",
    "promotionTag": "특가"
  },
  {
    "id": 9,
    "airlineName": "Japan Airlines",
    "country": "japan",
    "countryImage": "http://localhost:3333/images/country/japan.jpeg",
    "departureAirport": "ICN",
    "arrivalAirport": "NRT",
    "arrivalCountry": "일본",
    "outboundDate": "2024-07-18",
    "inboundDate": "2024-07-23",
    "price": 290000,
    "currency": "KRW",
    "promotionTag": "한정"
  },
  {
    "id": 10,
    "airlineName": "Thai Airways",
    "country": "thailand",
    "countryImage": "http://localhost:3333/images/country/thailand.jpeg",
    "departureAirport": "ICN",
    "arrivalAirport": "BKK",
    "arrivalCountry": "태국",
    "outboundDate": "2024-09-12",
    "inboundDate": "2024-09-17",
    "price": 310000,
    "currency": "KRW",
    "promotionTag": "특가"
  }
]
