[
  {
    "id": 1,
    "rating": 5,
    "breakfastIncluded": true,
    "amenities": ["와이파이", "야외 수영장", "스파"],
    "airportShuttle": true,
    "nearbyRestaurants": ["Blue Elephant", "Thip Samai Pad Thai"],
    "customerRating": 4.7
  },
  {
    "id": 2,
    "rating": 4,
    "breakfastIncluded": false,
    "amenities": ["와이파이", "피트니스 센터"],
    "airportShuttle": false,
    "nearbyRestaurants": ["Sushi Zanmai", "Ramen Ichiran"],
    "customerRating": 4.3
  },
  {
    "id": 3,
    "rating": 5,
    "breakfastIncluded": true,
    "amenities": ["실내 수영장", "피트니스 센터", "스파"],
    "airportShuttle": true,
    "nearbyRestaurants": ["Sala Rim Naam", "Bo.lan"],
    "customerRating": 4.8
  },
  {
    "id": 4,
    "rating": 3,
    "breakfastIncluded": false,
    "amenities": ["와이파이"],
    "airportShuttle": false,
    "nearbyRestaurants": ["Shake Shack", "Joe’s Pizza"],
    "customerRating": 4.0
  },
  {
    "id": 5,
    "rating": 4,
    "breakfastIncluded": true,
    "amenities": ["야외 수영장", "공항 셔틀"],
    "airportShuttle": true,
    "nearbyRestaurants": ["Paesano’s", "Buca di Beppo"],
    "customerRating": 4.2
  },
  {
    "id": 6,
    "rating": 5,
    "breakfastIncluded": true,
    "amenities": ["와이파이", "스파", "피트니스"],
    "airportShuttle": true,
    "nearbyRestaurants": ["La Tour d’Argent", "Café de Flore"],
    "customerRating": 4.9
  },
  {
    "id": 7,
    "rating": 3,
    "breakfastIncluded": false,
    "amenities": ["와이파이"],
    "airportShuttle": false,
    "nearbyRestaurants": ["Din Tai Fung", "Night Market Stalls"],
    "customerRating": 4.1
  },
  {
    "id": 8,
    "rating": 4,
    "breakfastIncluded": true,
    "amenities": ["와이파이", "피트니스 센터"],
    "airportShuttle": true,
    "nearbyRestaurants": ["El Celler de Can Roca", "Les Cols"],
    "customerRating": 4.6
  },
  {
    "id": 9,
    "rating": 4,
    "breakfastIncluded": false,
    "amenities": ["야외 수영장", "와이파이"],
    "airportShuttle": false,
    "nearbyRestaurants": ["Tiger’s Milk", "Kloof Street House"],
    "customerRating": 4.2
  },
  {
    "id": 10,
    "rating": 5,
    "breakfastIncluded": true,
    "amenities": ["실내 수영장", "스파", "레스토랑"],
    "airportShuttle": true,
    "nearbyRestaurants": ["Nobu", "Zuma Dubai"],
    "customerRating": 4.8
  },
  {
    "id": 11,
    "rating": 3,
    "breakfastIncluded": false,
    "amenities": ["와이파이"],
    "airportShuttle": false,
    "nearbyRestaurants": ["Street Food Alley", "Local BBQ"],
    "customerRating": 3.9
  },
  {
    "id": 12,
    "rating": 4,
    "breakfastIncluded": true,
    "amenities": ["피트니스 센터", "와이파이"],
    "airportShuttle": false,
    "nearbyRestaurants": ["The Test Kitchen", "Codfather"],
    "customerRating": 4.3
  },
  {
    "id": 13,
    "rating": 5,
    "breakfastIncluded": true,
    "amenities": ["와이파이", "루프탑 바", "피트니스"],
    "airportShuttle": true,
    "nearbyRestaurants": ["Quince", "Alinea"],
    "customerRating": 4.7
  },
  {
    "id": 14,
    "rating": 4,
    "breakfastIncluded": false,
    "amenities": ["와이파이", "공항 셔틀"],
    "airportShuttle": true,
    "nearbyRestaurants": ["L’Atelier", "Maison Kayser"],
    "customerRating": 4.5
  },
  {
    "id": 15,
    "rating": 5,
    "breakfastIncluded": true,
    "amenities": ["야외 수영장", "스파", "레스토랑"],
    "airportShuttle": true,
    "nearbyRestaurants": ["Khao", "Nahm"],
    "customerRating": 4.9
  },
  {
    "id": 16,
    "rating": 4,
    "breakfastIncluded": true,
    "amenities": ["실내 수영장", "피트니스"],
    "airportShuttle": true,
    "nearbyRestaurants": ["Ichiran", "Matsuya"],
    "customerRating": 4.4
  },
  {
    "id": 17,
    "rating": 3,
    "breakfastIncluded": false,
    "amenities": ["와이파이"],
    "airportShuttle": false,
    "nearbyRestaurants": ["Local Noodle Shop", "BBQ House"],
    "customerRating": 3.8
  },
  {
    "id": 18,
    "rating": 4,
    "breakfastIncluded": true,
    "amenities": ["야외 수영장", "공항 셔틀"],
    "airportShuttle": true,
    "nearbyRestaurants": ["Ocean Basket", "Local Grill"],
    "customerRating": 4.3
  },
  {
    "id": 19,
    "rating": 5,
    "breakfastIncluded": true,
    "amenities": ["와이파이", "스파", "루프탑"],
    "airportShuttle": true,
    "nearbyRestaurants": ["Fusion 88", "Tandoori Nights"],
    "customerRating": 4.6
  },
  {
    "id": 20,
    "rating": 4,
    "breakfastIncluded": false,
    "amenities": ["피트니스 센터", "와이파이"],
    "airportShuttle": false,
    "nearbyRestaurants": ["Simple Cafe", "Urban Diner"],
    "customerRating": 4.2
  },
  {
    "id": 21,
    "rating": 5,
    "breakfastIncluded": true,
    "amenities": ["와이파이", "레스토랑", "피트니스"],
    "airportShuttle": true,
    "nearbyRestaurants": ["Maison Pierre", "Tokyo Table"],
    "customerRating": 4.8
  },
  {
    "id": 22,
    "rating": 4,
    "breakfastIncluded": false,
    "amenities": ["야외 수영장", "와이파이"],
    "airportShuttle": false,
    "nearbyRestaurants": ["Oasis Cafe", "Sweet Sunset"],
    "customerRating": 4.1
  },
  {
    "id": 23,
    "rating": 5,
    "breakfastIncluded": true,
    "amenities": ["스파", "루프탑 바", "피트니스"],
    "airportShuttle": true,
    "nearbyRestaurants": ["Skyline Grill", "Roma Pizza"],
    "customerRating": 4.9
  },
  {
    "id": 24,
    "rating": 3,
    "breakfastIncluded": false,
    "amenities": ["와이파이"],
    "airportShuttle": false,
    "nearbyRestaurants": ["Local Deli", "Corner Cafe"],
    "customerRating": 3.7
  },
  {
    "id": 25,
    "rating": 4,
    "breakfastIncluded": true,
    "amenities": ["와이파이", "야외 수영장"],
    "airportShuttle": true,
    "nearbyRestaurants": ["Sunset Bistro", "Marina Cafe"],
    "customerRating": 4.5
  },
  {
    "id": 26,
    "rating": 5,
    "breakfastIncluded": true,
    "amenities": ["와이파이", "스파", "피트니스 센터"],
    "airportShuttle": true,
    "nearbyRestaurants": ["Fine Dine", "Chef’s Table"],
    "customerRating": 4.8
  },
  {
    "id": 27,
    "rating": 4,
    "breakfastIncluded": false,
    "amenities": ["와이파이", "피트니스"],
    "airportShuttle": false,
    "nearbyRestaurants": ["Casual Eats", "Bistro 27"],
    "customerRating": 4.0
  }
]
